LICENSE.txt
triotp-0.3.1.dist-info/METADATA
triotp-0.3.1.dist-info/WHEEL
triotp-0.3.1.dist-info/entry_points.txt
triotp-0.3.1.dist-info/licenses/LICENSE.txt
triotp/__init__.py
triotp/application.py
triotp/dynamic_supervisor.py
triotp/gen_server.py
triotp/helpers.py
triotp/logging.py
triotp/mailbox.py
triotp/node.py
triotp/supervisor.py
triotp-0.3.1.dist-info/RECORD
