Metadata-Version: 2.1
Name: triotp
Version: 0.3.1
Summary: The OTP framework for Python Trio
Keywords: trio,async,otp,triotp
Author-Email: David Delassus <david.jose.delassus@gmail.com>
License: MIT
Classifier: Development Status :: 4 - Beta
Classifier: Framework :: Trio
Classifier: Intended Audience :: Developers
Classifier: Topic :: Software Development
Project-URL: homepage, https://linkdd.github.io/triotp
Project-URL: repository, https://github.com/linkdd/triotp
Requires-Python: >=3.13
Requires-Dist: trio>=0.29.0
Requires-Dist: tenacity>=9.0.0
Requires-Dist: Logbook>=1.8.1
